{"name":"Archaeopteryx","size":"Tiny","subtype":"","group":null,"alignment":"unaligned","armor_class":12,"armor_desc":"natural armor","hit_points":7,"hit_dice":"3d4","speed":{"fly":50,"walk":5},"strength":6,"dexterity":13,"constitution":10,"intelligence":2,"wisdom":14,"charisma":6,"strength_save":null,"dexterity_save":null,"constitution_save":null,"intelligence_save":null,"wisdom_save":null,"charisma_save":null,"perception":null,"skills":{},"damage_vulnerabilities":"","damage_resistances":"","damage_immunities":"","condition_immunities":"","senses":"passive Perception 12","languages":"—","challenge_rating":"1/4","actions":[{"desc":"The archaeopteryx makes two attacks: one with its beak and one with its talons.","name":"Multiattack"},{"attack_bonus":3,"damage_dice":"1d4+1","desc":"Melee Weapon Attack: +3 to hit, reach 5 ft., one target. Hit: 3 (1d4 + 1) piercing damage.","name":"Beak"},{"attack_bonus":3,"damage_dice":"1d4+1","desc":"Melee Weapon Attack: +3 to hit, reach 5 ft., one target. Hit: 3 (1d4 + 1) slashing damage.","name":"Talons"}],"reactions":"","legendary_desc":"","legendary_actions":"","special_abilities":[{"desc":"The archaeopteryx doesn’t provoke opportunity attacks when it flies out of an enemy’s reach.","name":"Flyby"}],"spell_list":[],"img_main":null,"document__slug":"cc","document__title":"Creature Codex OGL","document__license_url":"http://open5e.com/legal","id":"archaeopteryx","type":"beast"}