{"name":"Roachling Skirmisher","size":"Small","subtype":"roachling","group":null,"alignment":"chaotic neutral","armor_class":13,"armor_desc":"natural armor","hit_points":7,"hit_dice":"2d6","speed":{"walk":25},"strength":10,"dexterity":14,"constitution":11,"intelligence":10,"wisdom":9,"charisma":8,"strength_save":null,"dexterity_save":4,"constitution_save":2,"intelligence_save":null,"wisdom_save":null,"charisma_save":null,"perception":null,"skills":{"acrobatics":4,"stealth":6},"damage_vulnerabilities":"","damage_resistances":"","damage_immunities":"","condition_immunities":"","senses":"darkvision 60 ft., tremorsense 10 ft., passive Perception 9","languages":"Common","challenge_rating":"1/4","actions":[{"name":"Shortsword","desc":"Melee Weapon Attack: +4 to hit, reach 5 ft., one target. Hit: 5 (1d6 + 2) piercing damage.","attack_bonus":4,"damage_dice":"1d6"},{"name":"Dart","desc":"Ranged Weapon Attack: +4 to hit, range 20/60 ft., one target. Hit: 4 (1d4 + 2) piercing damage.","attack_bonus":4,"damage_dice":"1d4"}],"reactions":"","legendary_desc":"","legendary_actions":"","special_abilities":[{"name":"Resistant","desc":"The roachling skirmisher has advantage on Constitution saving throws."},{"name":"Unlovely","desc":"The skirmisher has disadvantage on Performance and Persuasion checks in interactions with nonroachlings."}],"spell_list":[],"img_main":null,"document__slug":"tob","document__title":"Tome of Beasts OGL","document__license_url":"http://open5e.com/legal","id":"roachling-skirmisher","type":"humanoid"}