{"name":"Wyrmling Wind Dragon","size":"Medium","subtype":"","group":null,"alignment":"chaotic neutral","armor_class":14,"armor_desc":"","hit_points":45,"hit_dice":"7d8 + 14","speed":{"walk":40,"fly":80},"strength":16,"dexterity":19,"constitution":14,"intelligence":12,"wisdom":11,"charisma":14,"strength_save":null,"dexterity_save":6,"constitution_save":4,"intelligence_save":null,"wisdom_save":2,"charisma_save":4,"perception":4,"skills":{"perception":4,"stealth":6},"damage_vulnerabilities":"","damage_resistances":"","damage_immunities":"lightning","condition_immunities":"charmed, exhausted, paralyzed","senses":"blindsight 10 ft., darkvision 60 ft., passive Perception 14","languages":"Draconic, Primordial","challenge_rating":"1","actions":[{"name":"Bite","desc":"Melee Weapon Attack: +6 to hit, reach 5 ft., one target. Hit: 9 (1d10 + 4) piercing damage.","attack_bonus":6,"damage_dice":"1d10"},{"name":"Breath of Gales (Recharge 5-6)","desc":"The dragon exhales a blast of wind in a 15-foot cone. Each creature in that cone must make a successful DC 12 Strength saving throw or be pushed 15 feet away from the dragon and knocked prone. Unprotected flames in the cone are extinguished, and sheltered flames (such as those in lanterns) have a 50 percent chance of being extinguished."}],"reactions":"","legendary_desc":"","legendary_actions":"","special_abilities":"","spell_list":[],"img_main":null,"document__slug":"tob","document__title":"Tome of Beasts OGL","document__license_url":"http://open5e.com/legal","id":"wyrmling-wind-dragon","type":"dragon"}